{
    "date": "2025-05-15",
    "customer": "oioioioi",
    "customer_email": "lucavanov8@gmail.com",
    "address": "",
    "offer_description": "fheqigfqeub ougfoeqh fuqepi gfpqie fpiqepfihqepifgqephiòf fheqigfqeub ougfoeqh fuqepi gfpqie fpiqepfihqepifgqephiòf  fheqigfqeub ougfoeqh fuqepi gfpqie fpiqepfihqepifgqephiòf  fheqigfqeub ougfoeqh fuqepi gfpqie fpiqepfihqepifgqephiòf  fheqigfqeub ougfoeqh fuqepi gfpqie fpiqepfihqepifgqephiòf  fheqigfqeub ougfoeqh fuqepi gfpqie fpiqepfihqepifgqephiòf  fheqigfqeub ougfoeqh fuqepi gfpqie fpiqepfihqepifgqephiòf  fheqigfqeub ougfoeqh fuqepi gfpqie fpiqepfihqepifgqephiòf  fheqigfqeub ougfoeqh fuqepi gfpqie fpiqepfihqepifgqephiòf fheqigfqeub ougfoeqh fuqepi gfpqie fpiqepfihqepifgqephiòf  fheqigfqeub ougfoeqh fuqepi gfpqie fpiqepfihqepifgqephiòf  fheqigfqeub ougfoeqh fuqepi gfpqie fpiqepfihqepifgqephiòf  fheqigfqeub ougfoeqh fuqepi gfpqie fpiqepfihqepifgqephiòf fheqigfqeub ougfoeqh fuqepi gfpqie fpiqepfihqepifgqephiòf  fheqigfqeub ougfoeqh fuqepi gfpqie fpiqepfihqepifgqephiòf  fheqigfqeub ougfoeqh fuqepi gfpqie fpiqepfihqepifgqephiòf  fheqigfqeub ougfoeqh fuqepi gfpqie fpiqepfihqepifgqephiòf  fheqigfqeub ougfoeqh fuqepi gfpqie fpiqepfihqepifgqephiòf  fheqigfqeub ougfoeqh fuqepi gfpqie fpiqepfihqepifgqephiòf ",
    "offer_number": "2025-0098",
    "id": "40f8e51a-342f-4800-9ea9-bcafd14bb1cb",
    "tabs": [
        {
            "type": "single_product",
            "product_code": "",
            "product_name": "vhdqljbvldsjab",
            "quantity": "1",
            "unit_price": "3423",
            "description": "",
            "discount": "0",
            "discount_flag": false,
            "power_w": "",
            "volts": "",
            "size": "",
            "posizione": "7",
            "product_image_path": ""
        }
    ],
    "pdf_path": "offerta_2025-0098.pdf"
}